vllmlp/__init__.py
vllmlp/qwen.py
vllmlp/data/qwen-cjk.npy
vllmlp-0.0.2.dist-info/METADATA
vllmlp-0.0.2.dist-info/WHEEL
vllmlp-0.0.2.dist-info/top_level.txt
vllmlp-0.0.2.dist-info/RECORD
