Metadata-Version: 2.1
Name: vllmlp
Version: 0.0.2
Summary: Collections of Logits Processors for VLLM
Requires-Python: >=3.10
